{
  "$schema": "https://ui.shadcn.com/schema/registry-item.json",
  "name": "pricing-plans",
  "title": "Pricing Plans",
  "description": "An animated pricing section with billing toggles, review proof, plan cards, feature lists, and brand logos.",
  "dependencies": [
    "gsap",
    "@gsap/react",
    "lucide-react"
  ],
  "files": [
    {
      "path": "src/components/lemonade/pricing-plans.tsx",
      "content": "\"use client\"\n\nimport { type ComponentPropsWithoutRef, useMemo, useRef, useState } from \"react\"\nimport { Check, Star } from \"lucide-react\"\nimport gsap from \"gsap\"\nimport { useGSAP } from \"@gsap/react\"\n\nimport { usePrefersReducedMotion } from \"@/hooks/use-prefers-reduced-motion\"\nimport { cn } from \"@/lib/utils\"\n\nexport type PricingBillingCycle = \"monthly\" | \"annual\"\n\nexport type PricingPlan = {\n  name: string\n  monthlyPrice: number\n  annualPrice?: number\n  unit?: string\n  period?: string\n  description: string\n  featureIntro: string\n  features: string[]\n  badge?: string\n}\n\nexport type PricingReviewAvatar = {\n  label: string\n  src?: string\n  color?: string\n}\n\nexport type PricingPlansProps = Omit<ComponentPropsWithoutRef<\"section\">, \"title\"> & {\n  title?: string\n  accentTitle?: string\n  defaultBilling?: PricingBillingCycle\n  annualDiscount?: number\n  plans?: PricingPlan[]\n  logos?: string[]\n  avatars?: PricingReviewAvatar[]\n  rating?: string\n  reviewText?: string\n  onBillingChange?: (billing: PricingBillingCycle) => void\n  onPlanSelect?: (plan: PricingPlan, billing: PricingBillingCycle) => void\n}\n\nconst defaultPlans: PricingPlan[] = [\n  {\n    name: \"Basic plan\",\n    monthlyPrice: 10,\n    unit: \"per user\",\n    period: \"per month\",\n    description: \"Basic features for up to 10 users.\",\n    featureIntro: \"Everything in our free plan plus....\",\n    features: [\n      \"Access to basic features\",\n      \"Basic reporting and analytics\",\n      \"Up to 10 individual users\",\n      \"20GB individual data each user\",\n    ],\n  },\n  {\n    name: \"Business plan\",\n    monthlyPrice: 20,\n    unit: \"per user\",\n    period: \"per month\",\n    description: \"Basic features for up to 20 users.\",\n    featureIntro: \"Everything in Basic plus....\",\n    features: [\n      \"200+ integrations\",\n      \"Advanced reporting and analytics\",\n      \"Up to 20 individual users\",\n      \"40GB individual data each user\",\n    ],\n    badge: \"Popular\",\n  },\n  {\n    name: \"Enterprise plan\",\n    monthlyPrice: 40,\n    unit: \"per user\",\n    period: \"per month\",\n    description: \"Advanced features + unlimited users.\",\n    featureIntro: \"Everything in Business plus....\",\n    features: [\n      \"Advanced custom fields\",\n      \"Audit log and data history\",\n      \"Unlimited individual users\",\n      \"Unlimited individual data\",\n    ],\n  },\n]\n\nconst defaultLogos = [\"upwork\", \"PLAID\", \"splunk>\", \"ghost\", \"Square\", \"Wealthsimple\", \"Uber\", \"twitch\"]\n\nconst defaultAvatars: PricingReviewAvatar[] = [\n  { label: \"Jay\", color: \"#c98958\" },\n  { label: \"Noa\", color: \"#2d3946\" },\n  { label: \"Rae\", color: \"#f0d7bf\" },\n  { label: \"Mia\", color: \"#38302b\" },\n  { label: \"Ana\", color: \"#e2b9a8\" },\n]\n\nexport function PricingPlans({\n  title = \"We've got a plan\",\n  accentTitle = \"that's perfect for you\",\n  defaultBilling = \"monthly\",\n  annualDiscount = 0.16,\n  plans = defaultPlans,\n  logos = defaultLogos,\n  avatars = defaultAvatars,\n  rating = \"5.0\",\n  reviewText = \"from 4,000+ reviews\",\n  onBillingChange,\n  onPlanSelect,\n  className,\n  ...props\n}: PricingPlansProps) {\n  const rootRef = useRef<HTMLElement>(null)\n  const billingRef = useRef<HTMLDivElement>(null)\n  const reducedMotion = usePrefersReducedMotion()\n  const [billing, setBilling] = useState<PricingBillingCycle>(defaultBilling)\n  const saveLabel = useMemo(() => `Save ${Math.round(annualDiscount * 100)}%`, [annualDiscount])\n\n  useGSAP(\n    () => {\n      if (!rootRef.current || reducedMotion) {\n        return\n      }\n\n      const context = gsap.context(() => {\n        gsap.fromTo(\n          \"[data-pricing-intro]\",\n          { y: 22, opacity: 0 },\n          { y: 0, opacity: 1, duration: 0.78, ease: \"power3.out\", stagger: 0.08 }\n        )\n\n        gsap.fromTo(\n          \"[data-pricing-card]\",\n          { y: 28, opacity: 0, scale: 0.98 },\n          {\n            y: 0,\n            opacity: 1,\n            scale: 1,\n            duration: 0.72,\n            ease: \"power3.out\",\n            stagger: 0.08,\n            delay: 0.12,\n          }\n        )\n\n        gsap.fromTo(\n          \"[data-pricing-logo]\",\n          { y: 12, opacity: 0 },\n          { y: 0, opacity: 1, duration: 0.5, ease: \"power3.out\", stagger: 0.045, delay: 0.36 }\n        )\n      }, rootRef)\n\n      return () => context.revert()\n    },\n    { dependencies: [reducedMotion], scope: rootRef }\n  )\n\n  const setBillingCycle = (nextBilling: PricingBillingCycle) => {\n    setBilling(nextBilling)\n    onBillingChange?.(nextBilling)\n\n    if (reducedMotion || !rootRef.current) {\n      return\n    }\n\n    gsap.fromTo(\n      rootRef.current.querySelectorAll(\"[data-price-value]\"),\n      { y: 12, opacity: 0, filter: \"blur(5px)\" },\n      { y: 0, opacity: 1, filter: \"blur(0px)\", duration: 0.38, ease: \"power3.out\", stagger: 0.04 }\n    )\n\n    gsap.fromTo(\n      billingRef.current,\n      { scale: 0.98 },\n      { scale: 1, duration: 0.45, ease: \"elastic.out(1, 0.55)\" }\n    )\n  }\n\n  const liftCard = (card: HTMLElement) => {\n    if (reducedMotion) {\n      return\n    }\n\n    gsap.to(card, {\n      y: -8,\n      scale: 1.012,\n      duration: 0.34,\n      ease: \"power3.out\",\n    })\n  }\n\n  const settleCard = (card: HTMLElement) => {\n    if (reducedMotion) {\n      return\n    }\n\n    gsap.to(card, {\n      y: 0,\n      scale: 1,\n      duration: 0.5,\n      ease: \"elastic.out(1, 0.72)\",\n    })\n  }\n\n  return (\n    <section\n      ref={rootRef}\n      className={cn(\"mx-auto w-full max-w-[69rem] bg-white px-7 py-10 text-[#202124]\", className)}\n      {...props}\n    >\n      <div className=\"flex flex-col gap-8 md:flex-row md:items-start md:justify-between\">\n        <div className=\"min-w-0\">\n          <h2\n            data-pricing-intro\n            className=\"max-w-[48rem] text-5xl font-normal leading-[0.95] tracking-normal text-[#202124] sm:text-6xl lg:text-[4.35rem]\"\n          >\n            <span className=\"block\">{title}</span>\n            <span className=\"mt-3 block font-serif italic\">{accentTitle}</span>\n          </h2>\n\n          <div\n            ref={billingRef}\n            data-pricing-intro\n            className=\"mt-12 inline-flex items-center rounded-lg border border-[#d7d7d7] bg-[#f6f6f6] p-1 shadow-[0_3px_12px_rgba(0,0,0,0.06)]\"\n            aria-label=\"Pricing billing period\"\n          >\n            <BillingButton\n              active={billing === \"monthly\"}\n              onClick={() => setBillingCycle(\"monthly\")}\n              label=\"Monthly billing\"\n            />\n            <BillingButton\n              active={billing === \"annual\"}\n              onClick={() => setBillingCycle(\"annual\")}\n              label=\"Annual billing\"\n            />\n            <span className=\"ml-1 rounded-md bg-[#ededed] px-3 py-2 text-sm font-bold leading-none text-[#202124]/74\">\n              {saveLabel}\n            </span>\n          </div>\n        </div>\n\n        <div data-pricing-intro className=\"flex shrink-0 items-start gap-3 pt-3\">\n          <div className=\"flex -space-x-2 overflow-visible\">\n            {avatars.slice(0, 5).map((avatar, index) => (\n              <span\n                key={`${avatar.label}-${index}`}\n                tabIndex={0}\n                data-avatar-index={index}\n                aria-label={`${avatar.label} review`}\n                className=\"group/avatar relative grid size-8 place-items-center overflow-visible rounded-full outline-none hover:z-20 focus:z-20\"\n              >\n                <span\n                  data-avatar-tooltip\n                  role=\"tooltip\"\n                  className=\"pointer-events-none absolute -top-8 left-1/2 z-20 -translate-x-1/2 translate-y-1 scale-95 select-none whitespace-nowrap rounded-md border border-[#202124]/10 bg-white px-2 py-1 text-[0.66rem] font-black leading-none text-[#202124] opacity-0 shadow-[0_8px_18px_rgba(0,0,0,0.09)] transition-[opacity,transform] delay-75 duration-150 ease-out group-hover/avatar:translate-y-0 group-hover/avatar:scale-100 group-hover/avatar:opacity-100 group-focus/avatar:translate-y-0 group-focus/avatar:scale-100 group-focus/avatar:opacity-100\"\n                >\n                  {avatar.label}\n                  <span className=\"absolute left-1/2 top-full size-2 -translate-x-1/2 -translate-y-1 rotate-45 border-b border-r border-[#202124]/10 bg-white\" />\n                </span>\n                <span\n                  data-avatar-bubble\n                  className=\"grid size-8 select-none place-items-center overflow-hidden rounded-full border-2 border-white bg-[#ddd] text-[0.62rem] font-black text-white shadow-[0_4px_10px_rgba(0,0,0,0.1)] transition-transform duration-200 ease-out group-hover/avatar:-translate-y-1 group-hover/avatar:scale-105 group-focus/avatar:-translate-y-1 group-focus/avatar:scale-105\"\n                  style={{ background: avatar.color }}\n                >\n                  {avatar.src ? (\n                    // eslint-disable-next-line @next/next/no-img-element\n                    <img src={avatar.src} alt={avatar.label} className=\"size-full object-cover\" />\n                  ) : (\n                    avatar.label.slice(0, 1)\n                  )}\n                </span>\n              </span>\n            ))}\n          </div>\n          <div className=\"pt-0.5\">\n            <div className=\"flex gap-0.5\" aria-label={`${rating} star rating`}>\n              {Array.from({ length: 5 }).map((_, index) => (\n                <Star key={index} className=\"size-4 fill-[#202124] text-[#202124]\" strokeWidth={2.6} />\n              ))}\n              <span className=\"ml-1 text-sm font-black leading-none text-[#202124]\">{rating}</span>\n            </div>\n            <p className=\"mt-1 text-sm font-semibold leading-none text-[#202124]/54\">{reviewText}</p>\n          </div>\n        </div>\n      </div>\n\n      <div className=\"mt-14 grid gap-7 lg:grid-cols-3\">\n        {plans.map((plan) => {\n          const price = getPrice(plan, billing, annualDiscount)\n\n          return (\n            <article\n              key={plan.name}\n              data-pricing-card\n              className=\"overflow-hidden rounded-[1.35rem] border border-[#d7d7d7] bg-white shadow-[0_1px_0_rgba(0,0,0,0.02)]\"\n              onPointerEnter={(event) => liftCard(event.currentTarget)}\n              onPointerLeave={(event) => settleCard(event.currentTarget)}\n            >\n              <div className=\"p-7\">\n                <div className=\"flex min-h-7 items-start justify-between gap-3\">\n                  <h3 className=\"text-2xl font-black leading-none tracking-normal text-[#202124]\">\n                    {plan.name}\n                  </h3>\n                  {plan.badge ? (\n                    <span className=\"rounded-lg bg-[#f2f2f2] px-3 py-2 text-xs font-black leading-none text-[#202124]/68\">\n                      {plan.badge}\n                    </span>\n                  ) : null}\n                </div>\n\n                <div className=\"mt-7 flex items-end gap-2\">\n                  <span className=\"text-5xl font-black leading-none tracking-normal text-[#202124] sm:text-6xl\">\n                    $\n                  </span>\n                  <span\n                    data-price-value\n                    className=\"text-6xl font-black leading-[0.82] tracking-normal text-[#202124] sm:text-7xl\"\n                  >\n                    {price}\n                  </span>\n                  <span className=\"mb-1.5 text-sm font-semibold leading-tight text-[#202124]/66\">\n                    {plan.unit ?? \"per user\"}\n                    <br />\n                    {plan.period ?? \"per month\"}\n                  </span>\n                </div>\n\n                <p className=\"mt-8 min-h-6 text-base font-semibold leading-normal text-[#202124]/58\">\n                  {plan.description}\n                </p>\n\n                <button\n                  type=\"button\"\n                  className=\"mt-8 h-12 w-full rounded-lg bg-[#202124] text-base font-bold tracking-normal text-white shadow-[inset_0_1px_0_rgba(255,255,255,0.16),0_8px_22px_rgba(0,0,0,0.08)] transition-colors hover:bg-black focus-visible:outline-none focus-visible:ring-4 focus-visible:ring-[#202124]/12\"\n                  onClick={() => onPlanSelect?.(plan, billing)}\n                >\n                  Get started\n                </button>\n              </div>\n\n              <div className=\"border-t border-[#d7d7d7] p-7\">\n                <p className=\"text-sm font-black uppercase text-[#202124]\">Features</p>\n                <p className=\"mt-2 text-base font-semibold text-[#202124]/58\">{plan.featureIntro}</p>\n\n                <ul className=\"mt-6 space-y-4\">\n                  {plan.features.map((feature) => (\n                    <li key={feature} className=\"flex items-center gap-3 text-base font-semibold text-[#202124]/64\">\n                      <span className=\"grid size-5 shrink-0 place-items-center rounded-full bg-[#98ff0a] text-[#202124]\">\n                        <Check className=\"size-3.5\" strokeWidth={4} />\n                      </span>\n                      <span>{feature}</span>\n                    </li>\n                  ))}\n                </ul>\n              </div>\n            </article>\n          )\n        })}\n      </div>\n\n      <div className=\"mt-14 flex flex-wrap items-center justify-between gap-x-9 gap-y-5\">\n        {logos.map((logo) => (\n          <span\n            key={logo}\n            data-pricing-logo\n            className=\"text-2xl font-black leading-none tracking-normal text-[#202124] opacity-90\"\n          >\n            {logo}\n          </span>\n        ))}\n      </div>\n    </section>\n  )\n}\n\nfunction BillingButton({\n  active,\n  label,\n  onClick,\n}: {\n  active: boolean\n  label: string\n  onClick: () => void\n}) {\n  return (\n    <button\n      type=\"button\"\n      aria-pressed={active}\n      className={cn(\n        \"rounded-md px-3 py-2 text-sm font-bold leading-none transition-colors\",\n        active\n          ? \"bg-white text-[#202124] shadow-[0_2px_9px_rgba(0,0,0,0.08)]\"\n          : \"text-[#202124]/55 hover:bg-white/70 hover:text-[#202124]\"\n      )}\n      onClick={onClick}\n    >\n      {label}\n    </button>\n  )\n}\n\nfunction getPrice(plan: PricingPlan, billing: PricingBillingCycle, annualDiscount: number) {\n  if (billing === \"monthly\") {\n    return plan.monthlyPrice\n  }\n\n  return plan.annualPrice ?? Math.round(plan.monthlyPrice * (1 - annualDiscount))\n}\n",
      "type": "registry:component",
      "target": "components/lemonade-ui/pricing-plans.tsx"
    },
    {
      "path": "src/hooks/use-prefers-reduced-motion.ts",
      "content": "\"use client\"\n\nimport { useSyncExternalStore } from \"react\"\n\nconst reducedMotionQuery = \"(prefers-reduced-motion: reduce)\"\n\nfunction subscribe(onStoreChange: () => void) {\n  const mediaQuery = window.matchMedia(reducedMotionQuery)\n\n  mediaQuery.addEventListener(\"change\", onStoreChange)\n\n  return () => {\n    mediaQuery.removeEventListener(\"change\", onStoreChange)\n  }\n}\n\nfunction getSnapshot() {\n  return window.matchMedia(reducedMotionQuery).matches\n}\n\nfunction getServerSnapshot() {\n  return false\n}\n\nexport function usePrefersReducedMotion() {\n  return useSyncExternalStore(subscribe, getSnapshot, getServerSnapshot)\n}\n",
      "type": "registry:hook",
      "target": "hooks/use-prefers-reduced-motion.ts"
    }
  ],
  "type": "registry:component"
}